pvxslibs/__init__.py
pvxslibs/ioc.py
pvxslibs/path.py
pvxslibs/version.py
pvxslibs/dbd/pvxsIoc.dbd
pvxslibs/include/pvxs/client.h
pvxslibs/include/pvxs/data.h
pvxslibs/include/pvxs/iochooks.h
pvxslibs/include/pvxs/log.h
pvxslibs/include/pvxs/netcommon.h
pvxslibs/include/pvxs/nt.h
pvxslibs/include/pvxs/server.h
pvxslibs/include/pvxs/sharedArray.h
pvxslibs/include/pvxs/sharedpv.h
pvxslibs/include/pvxs/source.h
pvxslibs/include/pvxs/srvcommon.h
pvxslibs/include/pvxs/unittest.h
pvxslibs/include/pvxs/util.h
pvxslibs/include/pvxs/version.h
pvxslibs/include/pvxs/versionNum.h
pvxslibs/lib/__init__.py
pvxslibs/lib/event_core_dsoinfo.py
pvxslibs/lib/event_pthread_dsoinfo.py
pvxslibs/lib/libevent_core.so
pvxslibs/lib/libevent_core.so.2.2.0
pvxslibs/lib/libevent_pthread.so
pvxslibs/lib/libevent_pthread.so.2.2.0
pvxslibs/lib/libpvxs.so
pvxslibs/lib/libpvxs.so.1.5
pvxslibs/lib/libpvxsIoc.so
pvxslibs/lib/libpvxsIoc.so.1.5
pvxslibs/lib/pvxsIoc_dsoinfo.py
pvxslibs/lib/pvxs_dsoinfo.py
pvxslibs/test/__init__.py
pvxslibs/test/test_load.py
pvxslibs-1.5.0.dist-info/licenses/LICENSE
pvxslibs-1.5.0.dist-info/METADATA
pvxslibs-1.5.0.dist-info/WHEEL
pvxslibs-1.5.0.dist-info/top_level.txt
pvxslibs-1.5.0.dist-info/RECORD
