Metadata-Version: 2.1
Name: pvxslibs
Version: 1.5.0
Summary: PVXS libraries packaged for python
Home-page: https://epics-base.github.io/pvxs
Author: Michael Davidsaver
Author-email: mdavidsaver@gmail.com
License: BSD
Keywords: epics scada
Classifier: Development Status :: 5 - Production/Stable
Classifier: Programming Language :: Python :: 2.7
Classifier: Programming Language :: Python :: 3
Classifier: Programming Language :: Python :: Implementation :: CPython
Classifier: Intended Audience :: Science/Research
Classifier: Topic :: Scientific/Engineering
Classifier: Topic :: Software Development :: Libraries
Classifier: Topic :: System :: Distributed Computing
Classifier: Operating System :: POSIX :: Linux
Classifier: Operating System :: MacOS
Classifier: Operating System :: Microsoft :: Windows
Requires-Python: >=2.7
License-File: LICENSE
Requires-Dist: setuptools-dso>=2.7a1
Requires-Dist: epicscorelibs<7.0.10.99.1,>=7.0.10.99.0.0
